plone.app.versioningbehavior-2.0.5-py3.13-nspkg.pth
plone/app/versioningbehavior/__init__.py
plone/app/versioningbehavior/behaviors.py
plone/app/versioningbehavior/browser.py
plone/app/versioningbehavior/configure.zcml
plone/app/versioningbehavior/modifiers.py
plone/app/versioningbehavior/setuphandlers.py
plone/app/versioningbehavior/subscribers.py
plone/app/versioningbehavior/testing.py
plone/app/versioningbehavior/todo.txt
plone/app/versioningbehavior/utils.py
plone/app/versioningbehavior/profiles/default/metadata.xml
plone/app/versioningbehavior/profiles/default/plone.app.versioningbehavior_various.txt
plone/app/versioningbehavior/tests/__init__.py
plone/app/versioningbehavior/tests/doctest_behavior.txt
plone/app/versioningbehavior/tests/test_IntegrationTests.py
plone/app/versioningbehavior/tests/test_browser.py
plone/app/versioningbehavior/tests/test_functional.py
plone/app/versioningbehavior/tests/test_modifiers.py
plone/app/versioningbehavior/tests/test_subscribers.py
plone/app/versioningbehavior/tests/tests.py
plone/app/versioningbehavior/www/CloneNamedFileBlobs.pt
plone/app/versioningbehavior/www/SkipRelations.pt
plone/app/versioningbehavior/www/modifier.gif
plone_app_versioningbehavior-2.0.5.dist-info/METADATA
plone_app_versioningbehavior-2.0.5.dist-info/WHEEL
plone_app_versioningbehavior-2.0.5.dist-info/entry_points.txt
plone_app_versioningbehavior-2.0.5.dist-info/namespace_packages.txt
plone_app_versioningbehavior-2.0.5.dist-info/top_level.txt
plone_app_versioningbehavior-2.0.5.dist-info/RECORD
