Metadata-Version: 2.4
Name: plone.app.versioningbehavior
Version: 2.0.5
Summary: Provides a behavior for using CMFEditions with dexterity content types
Home-page: http://plone.org/products/dexterity
Author: Jonas Baumann, 4teamwork GmbH
Author-email: mailto:dexterity-development@googlegroups.com
License: GPL version 2
Keywords: plone dexterity behavior versioning CMFEditions
Classifier: Development Status :: 5 - Production/Stable
Classifier: Environment :: Web Environment
Classifier: Framework :: Plone
Classifier: Framework :: Plone :: 6.0
Classifier: Framework :: Plone :: 6.1
Classifier: Framework :: Plone :: Core
Classifier: Framework :: Zope :: 5
Classifier: License :: OSI Approved :: GNU General Public License v2 (GPLv2)
Classifier: Operating System :: OS Independent
Classifier: Programming Language :: Python
Classifier: Programming Language :: Python :: 3.8
Classifier: Programming Language :: Python :: 3.9
Classifier: Programming Language :: Python :: 3.10
Classifier: Programming Language :: Python :: 3.11
Classifier: Programming Language :: Python :: 3.12
Classifier: Topic :: Software Development :: Libraries :: Python Modules
Requires-Python: >=3.8
Requires-Dist: plone.app.dexterity[relations]
Requires-Dist: plone.autoform
Requires-Dist: plone.base
Requires-Dist: plone.behavior>=1.1
Requires-Dist: plone.dexterity
Requires-Dist: plone.namedfile
Requires-Dist: plone.rfc822
Requires-Dist: plone.supermodel
Requires-Dist: Products.CMFEditions>2.2.9
Requires-Dist: Products.GenericSetup
Requires-Dist: setuptools
Requires-Dist: z3c.form
Requires-Dist: z3c.relationfield
Requires-Dist: Zope
Provides-Extra: tests
Requires-Dist: plone.app.contenttypes[test]; extra == "tests"
Requires-Dist: plone.app.robotframework; extra == "tests"
Requires-Dist: plone.app.testing; extra == "tests"
Requires-Dist: plone.protect; extra == "tests"
Requires-Dist: plone.testing; extra == "tests"
Requires-Dist: Products.CMFDiffTool; extra == "tests"
Requires-Dist: Products.CMFEditions[test]; extra == "tests"
Requires-Dist: zope.intid; extra == "tests"
Dynamic: author
Dynamic: author-email
Dynamic: classifier
Dynamic: description
Dynamic: description-content-type
Dynamic: home-page
Dynamic: keywords
Dynamic: license
Dynamic: provides-extra
Dynamic: requires-dist
Dynamic: requires-python
Dynamic: summary
